pybraries/__init__.py
pybraries/helpers.py
pybraries/make_request.py
pybraries/pagination.py
pybraries/search.py
pybraries/search_helpers.py
pybraries/subscribe.py
pybraries/subscription_helpers.py
pybraries-0.4.0.dist-info/LICENSE
pybraries-0.4.0.dist-info/METADATA
pybraries-0.4.0.dist-info/WHEEL
pybraries-0.4.0.dist-info/top_level.txt
pybraries-0.4.0.dist-info/RECORD
