Metadata-Version: 2.1
Name: pybraries
Version: 0.4.0
Summary: A Python wrapper for the libraries.io API
Home-page: https://github.com/pybraries/pybraries/
Author: Jeff Hale
Author-email: jeffmshale@gmail.com
License: UNKNOWN
Platform: UNKNOWN
Classifier: Development Status :: 4 - Beta
Classifier: Programming Language :: Python :: 3.7
Classifier: Programming Language :: Python :: 3.8
Classifier: Programming Language :: Python :: 3.9
Classifier: License :: OSI Approved :: BSD License
License-File: LICENSE
Requires-Dist: requests (>=2)
Requires-Dist: fire (>0.1.1)
Requires-Dist: urllib3
